linearbunny/__init__.py
linearbunny/config.py
linearbunny/linearbunny.py
linearbunny/server.py
linearbunny/strategy_interactive_plot.py
linearbunny-0.0.5.dist-info/LICENSE.txt
linearbunny-0.0.5.dist-info/METADATA
linearbunny-0.0.5.dist-info/WHEEL
linearbunny-0.0.5.dist-info/top_level.txt
linearbunny-0.0.5.dist-info/RECORD
