Metadata-Version: 2.1
Name: linearbunny
Version: 0.0.5
Summary: A linearbunny package
Home-page: https://github.com/yanruoyu2005/ruoyu_insightproject/linearbunny
Author: Ruoyu Yan
Author-email: yanruoyu2005@gmail.com
License: GPLv3+
Platform: UNKNOWN
Classifier: Programming Language :: Python :: 3
Classifier: License :: OSI Approved :: GNU General Public License v3 or later (GPLv3+)
Classifier: Operating System :: OS Independent
